mxd2jpg/__init__.py
mxd2jpg-1.0.1.dist-info/LICENSE
mxd2jpg-1.0.1.dist-info/METADATA
mxd2jpg-1.0.1.dist-info/WHEEL
mxd2jpg-1.0.1.dist-info/top_level.txt
mxd2jpg-1.0.1.dist-info/RECORD
