Metadata-Version: 2.1
Name: mxd2jpg
Version: 1.0.1
Summary: Esri's export to jpg
Home-page: https://github.com/ctnkyrd/esri-mxd2png
Author: Arda Cetinkaya
Author-email: ardacetinkaya@windowslive.com
License: UNKNOWN
Platform: UNKNOWN
Classifier: Programming Language :: Python :: 2
Classifier: License :: OSI Approved :: MIT License
Classifier: Operating System :: OS Independent
